RobotArm/Robotarm.py
RobotArm/__init__.py
RobotArm/network.py
HHS_Robotarm-0.0.1.11.dist-info/LICENCE
HHS_Robotarm-0.0.1.11.dist-info/METADATA
HHS_Robotarm-0.0.1.11.dist-info/WHEEL
HHS_Robotarm-0.0.1.11.dist-info/top_level.txt
HHS_Robotarm-0.0.1.11.dist-info/RECORD
