Metadata-Version: 2.1
Name: HHS-Robotarm
Version: 0.0.1.11
Summary: A Python package for interfacing with the HHS robot arm
Author-email: Luke Parker <luke.parker885@gmail.com>
Project-URL: Homepage, https://github.com/LParker885/HHS-Robot-Arm
Project-URL: Bug Tracker, https://github.com/LParker885/HHS-Robot-Arm/issues
Classifier: Programming Language :: Python :: 3
Classifier: License :: OSI Approved :: GNU General Public License v2 or later (GPLv2+)
Classifier: Operating System :: OS Independent
Requires-Python: >=3.7
License-File: LICENCE
